easyaidata/__init__.py
easyaidata/app.pyd
easyaidata/get_version.py
easyaidata/load.py
easyaidata/setup.py
easyaidata/core/agent.pyd
easyaidata/core/agent_ui.pyd
easyaidata/core/auto.pyd
easyaidata/core/clean.pyd
easyaidata/core/clean_pl.pyd
easyaidata/core/data_res.pyd
easyaidata/core/draw.pyd
easyaidata/core/empty.pyd
easyaidata/core/funtions.pyd
easyaidata/core/funtions_pl.pyd
easyaidata/core/hlp.pyd
easyaidata/core/llm2.pyd
easyaidata/core/open_and_close.pyd
easyaidata/core/open_and_close_pl.pyd
easyaidata/core/ror_and_tread_pd.pyd
easyaidata/core/ror_and_tread_pl.pyd
easyaidata/core/sample.pyd
easyaidata/core/skill_loader.pyd
easyaidata/core/skill_manager.pyd
easyaidata/core/skills.pyd
easyaidata/core/viewer.pyd
easyaidata/core/skills_plugins/PANDAS_OPERATIONS_README.md
easyaidata/core/skills_plugins/README.md
easyaidata/core/skills_plugins/SKILLS_README.md
easyaidata/core/skills_plugins/__init__.py
easyaidata/core/skills_plugins/data_cleaning.py
easyaidata/core/skills_plugins/data_cleaning_README.md
easyaidata/core/skills_plugins/data_masking.py
easyaidata/core/skills_plugins/data_masking_README.md
easyaidata/core/skills_plugins/groupby_and_pivot.py
easyaidata/core/skills_plugins/groupby_and_pivot_README.md
easyaidata/core/skills_plugins/llm_call.py
easyaidata/core/skills_plugins/llm_call_README.md
easyaidata/core/skills_plugins/open_data_pandas.py
easyaidata/core/skills_plugins/open_data_pandas_README.md
easyaidata/core/skills_plugins/open_draw_manager.py
easyaidata/core/skills_plugins/open_draw_manager_README.md
easyaidata/core/skills_plugins/open_in_new_tab_README.md
easyaidata/core/skills_plugins/open_table_viewer.py
easyaidata/core/skills_plugins/open_table_viewer_README.md
easyaidata/core/skills_plugins/open_text_viewer.py
easyaidata/core/skills_plugins/open_text_viewer_README.md
easyaidata/core/skills_plugins/pandas_operations.py
easyaidata/core/skills_plugins/ror_calculation.py
easyaidata/core/skills_plugins/ror_calculation_README.md
easyaidata-2.5.0.dist-info/licenses/LICENSE.txt
easyaidata-2.5.0.dist-info/METADATA
easyaidata-2.5.0.dist-info/WHEEL
easyaidata-2.5.0.dist-info/entry_points.txt
easyaidata-2.5.0.dist-info/top_level.txt
easyaidata-2.5.0.dist-info/RECORD
