Metadata-Version: 2.4
Name: easyaidata
Version: 2.5.0
Summary: A easy-to-use data processing tool with GUI
Home-page: https://pypi.org/project/easyaidata/
Author: sysucai
Author-email: 411703730@qq.com
License: Proprietary Non-Commercial
Platform: Windows
Classifier: Development Status :: 3 - Alpha
Classifier: Intended Audience :: Developers
Classifier: Intended Audience :: End Users/Desktop
Classifier: Topic :: Scientific/Engineering :: Information Analysis
Classifier: Programming Language :: Python :: 3
Classifier: Programming Language :: Python :: 3.8
Classifier: Programming Language :: Python :: 3.9
Classifier: Programming Language :: Python :: 3.10
Classifier: Programming Language :: Python :: 3.11
Classifier: Programming Language :: Python :: 3.12
Classifier: Programming Language :: Python :: 3.13
Classifier: Programming Language :: Python :: 3.14
Classifier: Operating System :: Microsoft :: Windows
Requires-Python: >=3.8
License-File: LICENSE.txt
Requires-Dist: pandas
Requires-Dist: numpy
Requires-Dist: Pillow
Requires-Dist: tksheet
Requires-Dist: polars>=0.0.1
Requires-Dist: pyarrow>=0.0.1
Requires-Dist: requests
Requires-Dist: python-docx
Requires-Dist: pydantic
Requires-Dist: matplotlib
Dynamic: author
Dynamic: author-email
Dynamic: classifier
Dynamic: home-page
Dynamic: license
Dynamic: license-file
Dynamic: platform
Dynamic: requires-dist
Dynamic: requires-python
Dynamic: summary
